<?xml version="1.0" encoding="UTF-8"?>
<!DOCTYPE plist PUBLIC "-//Apple//DTD PLIST 1.0//EN" "http://www.apple.com/DTDs/PropertyList-1.0.dtd"/>

<plist version="1.0">
    <dict>
        <key>ROOT</key>
        <array>
            <dict>
                <key>id</key>
                <string>136</string>
                <key>children</key>
                <array>
                    <string>884</string>
                </array>
            </dict>
            <dict>
                <key>id</key>
                <string>137</string>
                <key>Music</key>
                <dict>
                    <key>value</key>
                    <string>1246</string>
                </dict>
                <key>children</key>
                <array>
                    <string>817</string>
                    <string>822</string>
                    <string>827</string>
                    <string>840</string>
                    <string>925</string>
                    <string>986</string>
                    <string>1123</string>
                    <string>1280</string>
                    <string>1283</string>
                    <string>1289</string>
                    <string>1295</string>
                </array>
            </dict>
            <dict>
                <key>id</key>
                <string>138</string>
                <key>Music</key>
                <dict>
                    <key>value</key>
                    <string>1247</string>
                </dict>
                <key>children</key>
                <array>
                    <string>154</string>
                    <string>173</string>
                    <string>672</string>
                    <string>1194</string>
                </array>
            </dict>
            <dict>
                <key>id</key>
                <string>139</string>
                <key>Music</key>
                <dict>
                    <key>value</key>
                    <string>1256</string>
                </dict>
                <key>children</key>
                <array>
                    <string>492</string>
                    <string>552</string>
                    <string>557</string>
                    <string>611</string>
                    <string>613</string>
                    <string>937</string>
                    <string>943</string>
                    <string>960</string>
                    <string>965</string>
                    <string>967</string>
                    <string>975</string>
                </array>
            </dict>
            <dict>
                <key>id</key>
                <string>140</string>
                <key>children</key>
                <array>
                    <string>1148</string>
                    <string>1151</string>
                </array>
            </dict>
            <dict>
                <key>id</key>
                <string>144</string>
                <key>children</key>
                <array/>
            </dict>
            <dict>
                <key>id</key>
                <string>146</string>
                <key>children</key>
                <array/>
            </dict>
            <dict>
                <key>id</key>
                <string>151</string>
                <key>children</key>
                <array/>
            </dict>
        </array>
    </dict>
</plist>
